vault_check/__init__.py
vault_check/__main__.py
vault_check/banner.py
vault_check/bootstrap.py
vault_check/cli.py
vault_check/config.py
vault_check/dashboard.py
vault_check/exceptions.py
vault_check/heuristics.py
vault_check/http_client.py
vault_check/logger.py
vault_check/output.py
vault_check/plugins.py
vault_check/registry.py
vault_check/reporting.py
vault_check/runner.py
vault_check/secrets.py
vault_check/signals.py
vault_check/utils.py
vault_check/verifiers/__init__.py
vault_check/verifiers/accounts.py
vault_check/verifiers/base.py
vault_check/verifiers/database.py
vault_check/verifiers/google.py
vault_check/verifiers/jwt.py
vault_check/verifiers/razorpay.py
vault_check/verifiers/redis.py
vault_check/verifiers/s3.py
vault_check/verifiers/session_key.py
vault_check/verifiers/smtp.py
vault_check/verifiers/telegram.py
vault_check/verifiers/webhook.py
vault_check-7.0.0.dist-info/licenses/LICENSE
vault_check-7.0.0.dist-info/METADATA
vault_check-7.0.0.dist-info/WHEEL
vault_check-7.0.0.dist-info/entry_points.txt
vault_check-7.0.0.dist-info/top_level.txt
vault_check-7.0.0.dist-info/RECORD
