Metadata-Version: 2.4
Name: vault-check
Version: 7.0.0
Summary: Production-grade secrets verifier for bot platforms
Author-email: dhruv13x <dhruv13x@example.com>
License: MIT
Project-URL: Homepage, https://github.com/dhruv13x/vault-check
Project-URL: Source, https://github.com/dhruv13x/vault-check
Keywords: vault,secrets,env,cli,security
Classifier: Programming Language :: Python :: 3
Classifier: License :: OSI Approved :: MIT License
Classifier: Operating System :: OS Independent
Classifier: Development Status :: 4 - Beta
Classifier: Intended Audience :: Developers
Classifier: Topic :: Software Development :: Testing
Classifier: Topic :: System :: Systems Administration
Requires-Python: >=3.11
License-File: LICENSE
Requires-Dist: aiohttp>=3.8.0
Requires-Dist: python-dotenv>=1.0.0
Requires-Dist: rich>=13.0.0
Requires-Dist: cryptography>=41.0.0
Requires-Dist: zxcvbn>=4.4.28
Requires-Dist: boto3>=1.26.0
Requires-Dist: asyncpg>=0.29.0
Requires-Dist: aiosqlite>=0.19.0
Requires-Dist: redis[asyncio]>=4.5.0
Requires-Dist: hvac>=1.1.0
Provides-Extra: dev
Requires-Dist: pytest>=8.0.0; extra == "dev"
Requires-Dist: pytest-cov>=5.0.0; extra == "dev"
Requires-Dist: pytest-timeout>=2.2.0; extra == "dev"
Requires-Dist: pytest-json-report>=1.5.0; extra == "dev"
Requires-Dist: pytest-asyncio>=0.23.0; extra == "dev"
Requires-Dist: pytest-mock>=3.10.0; extra == "dev"
Requires-Dist: pytest-aiohttp>=1.0.0; extra == "dev"
Requires-Dist: pyfakefs>=5.0.0; extra == "dev"
Requires-Dist: ruff>=0.6.0; extra == "dev"
Requires-Dist: black>=24.3.0; extra == "dev"
Requires-Dist: mypy>=1.11.0; extra == "dev"
Requires-Dist: PyYAML>=6.0; extra == "dev"
Requires-Dist: types-PyYAML>=6.0; extra == "dev"
Dynamic: license-file
